odoo/addons/product_pricelist_assortment/README.rst
odoo/addons/product_pricelist_assortment/__init__.py
odoo/addons/product_pricelist_assortment/__manifest__.py
odoo/addons/product_pricelist_assortment/data/ir_cron.xml
odoo/addons/product_pricelist_assortment/i18n/ca.po
odoo/addons/product_pricelist_assortment/i18n/es.po
odoo/addons/product_pricelist_assortment/i18n/product_pricelist_assortment.pot
odoo/addons/product_pricelist_assortment/models/__init__.py
odoo/addons/product_pricelist_assortment/models/product_pricelist.py
odoo/addons/product_pricelist_assortment/models/product_pricelist_assortment_item.py
odoo/addons/product_pricelist_assortment/models/product_pricelist_item.py
odoo/addons/product_pricelist_assortment/readme/CONTRIBUTORS.rst
odoo/addons/product_pricelist_assortment/readme/DESCRIPTION.rst
odoo/addons/product_pricelist_assortment/security/product_pricelist_assortment_item.xml
odoo/addons/product_pricelist_assortment/static/description/icon.png
odoo/addons/product_pricelist_assortment/static/description/index.html
odoo/addons/product_pricelist_assortment/tests/__init__.py
odoo/addons/product_pricelist_assortment/tests/test_pricelist_assortment.py
odoo/addons/product_pricelist_assortment/views/product_pricelist.xml
odoo/addons/product_pricelist_assortment/views/product_pricelist_assortment_item.xml
odoo/addons/product_pricelist_assortment/views/product_pricelist_item.xml
odoo13_addon_product_pricelist_assortment-13.0.1.1.0.dist-info/METADATA
odoo13_addon_product_pricelist_assortment-13.0.1.1.0.dist-info/WHEEL
odoo13_addon_product_pricelist_assortment-13.0.1.1.0.dist-info/top_level.txt
odoo13_addon_product_pricelist_assortment-13.0.1.1.0.dist-info/RECORD
